go_template/__init__.py
go_template/wrapper.py
go_template/bind/template.h
go_template/bind/template.so
py_go_template-1.0.0.dist-info/LICENSE
py_go_template-1.0.0.dist-info/METADATA
py_go_template-1.0.0.dist-info/WHEEL
py_go_template-1.0.0.dist-info/top_level.txt
py_go_template-1.0.0.dist-info/RECORD
