Metadata-Version: 2.1
Name: py-go-template
Version: 1.0.0
Summary: Python bindings for go-template with helmfile/sprig functions
Author-email: myback <54638513+myback@users.noreply.github.com>
License: MIT License
Project-URL: Homepage, https://github.com/myback/go-template
Project-URL: Bug Tracker, https://github.com/myback/go-template/issues
Classifier: Programming Language :: Python :: 3.7
Classifier: Programming Language :: Python :: 3.8
Classifier: Programming Language :: Python :: 3.9
Classifier: Programming Language :: Python :: 3.10
Classifier: Programming Language :: Python :: 3.11
Classifier: License :: OSI Approved :: MIT License
Classifier: Operating System :: OS Independent
Requires-Python: >=3.7
License-File: LICENSE
